{"nodes": [{"string": "t;", "links": [], "variables": [], "ids": [], "nodeId": 0, "featuresSelf": [], "operators": [], "constants": [], "features": []}, {"string": "scanf", "links": [], "variables": ["t"], "ids": [], "nodeId": 1, "featuresSelf": ["in", "&%d"], "operators": ["&"], "constants": ["%d"], "features": ["&%d", "in"]}, {"string": " while ( t -- )", "links": [1], "variables": ["t"], "ids": [], "nodeId": 2, "featuresSelf": ["cn", "--"], "operators": ["--"], "constants": [], "features": ["--", "&%d", "cn", "in"]}, {"string": "char str[25000];", "links": [], "variables": ["str"], "ids": ["lp"], "nodeId": 3, "featuresSelf": ["25000"], "operators": [], "constants": ["25000"], "features": ["25000"]}, {"string": "char str2[25000];", "links": [], "variables": ["str2"], "ids": ["lp"], "nodeId": 4, "featuresSelf": ["25000"], "operators": [], "constants": ["25000"], "features": ["25000"]}, {"string": "char str3[25000];", "links": [], "variables": ["str3"], "ids": ["lp"], "nodeId": 5, "featuresSelf": ["25000"], "operators": [], "constants": ["25000"], "features": ["25000"]}, {"string": "scanf", "links": [3], "variables": ["str"], "ids": ["lp"], "nodeId": 6, "featuresSelf": ["in", "%s"], "operators": [], "constants": ["%s"], "features": ["25000", "%s", "in"]}, {"string": "scanf", "links": [4], "variables": ["str2"], "ids": ["lp"], "nodeId": 7, "featuresSelf": ["in", "%s"], "operators": [], "constants": ["%s"], "features": ["25000", "%s", "in"]}, {"string": "l1;", "links": [6], "variables": ["l1", "str", "strlen"], "ids": ["lp"], "nodeId": 8, "featuresSelf": [], "operators": [], "constants": [], "features": ["25000", "%s", "in"]}, {"string": "l2;", "links": [7, 8], "variables": ["l2", "str2", "strlen"], "ids": ["lp"], "nodeId": 9, "featuresSelf": [], "operators": [], "constants": [], "features": ["25000", "%s", "in"]}, {"string": "i;", "links": [], "variables": ["i"], "ids": ["lp"], "nodeId": 10, "featuresSelf": ["0", "0"], "operators": [], "constants": ["0", "0"], "features": ["0"]}, {"string": " l2 > l1", "links": [8, 9], "variables": ["l1", "l2"], "ids": ["lp"], "nodeId": 11, "featuresSelf": ["icn", ">"], "operators": [">"], "constants": [], "features": ["icn", ">"]}, {"string": " i < l2", "links": [11, 10], "variables": ["l2", "i"], "ids": ["lp", "if"], "nodeId": 12, "featuresSelf": ["<0"], "operators": ["<"], "constants": ["0"], "features": ["0", "icn", "<0", ">"]}, {"string": null, "links": [], "variables": [], "ids": ["lp", "if"], "nodeId": 13, "featuresSelf": ["cn"], "operators": [], "constants": [], "features": ["cn"]}, {"string": null, "links": [12], "variables": ["i"], "ids": ["lp", "if", "lp"], "nodeId": 14, "featuresSelf": ["++"], "operators": ["++"], "constants": [], "features": ["++", "0", "<0"]}, {"string": " str [ j ] == str2 [ i ]", "links": [9, 14, 8], "variables": ["str2", "i", "str", "j"], "ids": ["lp", "if", "lp"], "nodeId": 15, "featuresSelf": ["icn", "==", "++"], "operators": ["==", "++"], "constants": [], "features": ["25000", "icn", "<0", "0", "==", "++", "in", "%s"]}, {"string": " j == l1", "links": [11, 15], "variables": ["l1", "j"], "ids": ["lp", "if"], "nodeId": 16, "featuresSelf": ["icn", "out", "out", "==YES\\n", "==NO\\n"], "operators": ["=="], "constants": ["YES\\n", "NO\\n"], "features": ["icn", "==", "==NO\\n", "++", "==YES\\n", ">", "out"]}, {"string": " i < l1", "links": [16, 15], "variables": ["l1", "i"], "ids": ["lp"], "nodeId": 17, "featuresSelf": ["<0"], "operators": ["<"], "constants": ["0"], "features": ["icn", "<0", "==", "==NO\\n", "++", "0", "==YES\\n", "out", ">"]}, {"string": null, "links": [], "variables": [], "ids": ["lp"], "nodeId": 18, "featuresSelf": ["cn"], "operators": [], "constants": [], "features": ["cn"]}, {"string": null, "links": [17], "variables": ["i"], "ids": ["lp", "lp"], "nodeId": 19, "featuresSelf": ["++"], "operators": ["++"], "constants": [], "features": ["==", "0", "icn", "<0", "++"]}, {"string": " str2 [ j ] == str [ i ]", "links": [15, 19, 15, 16], "variables": ["str", "i", "str2", "j"], "ids": ["lp", "lp"], "nodeId": 20, "featuresSelf": ["icn", "==", "++"], "operators": ["==", "++"], "constants": [], "features": ["25000", "icn", "<0", "0", "==", "==NO\\n", "++", "==YES\\n", "in", "%s", "out"]}, {"string": " j == l2", "links": [12, 20], "variables": ["l2", "j"], "ids": ["lp"], "nodeId": 21, "featuresSelf": ["icn", "out", "out", "==YES\\n", "==NO\\n"], "operators": ["=="], "constants": ["YES\\n", "NO\\n"], "features": ["icn", "<0", "==", "==NO\\n", "++", "==YES\\n", ">", "out"]}, {"string": " return 0", "links": [], "variables": [], "ids": [], "nodeId": 22, "featuresSelf": ["return", "0"], "operators": [], "constants": ["0"], "features": ["0", "return"]}]}