{"nodes": [{"string": "long;", "links": [], "variables": ["long"], "ids": [], "nodeId": 0, "featuresSelf": [], "operators": [], "constants": [], "features": []}, {"string": "char s[1000000];", "links": [], "variables": ["s"], "ids": [], "nodeId": 1, "featuresSelf": ["1000000"], "operators": [], "constants": ["1000000"], "features": ["1000000"]}, {"string": "scanf", "links": [], "variables": ["t"], "ids": [], "nodeId": 2, "featuresSelf": ["in", "&%lld"], "operators": ["&"], "constants": ["%lld"], "features": ["&%lld", "in"]}, {"string": " while ( t -- )", "links": [2], "variables": ["t"], "ids": [], "nodeId": 3, "featuresSelf": ["cn", "--"], "operators": ["--"], "constants": [], "features": ["--", "&%lld", "cn", "in"]}, {"string": "scanf", "links": [1], "variables": ["s"], "ids": ["lp"], "nodeId": 4, "featuresSelf": ["in", "%s"], "operators": [], "constants": ["%s"], "features": ["1000000", "%s", "in"]}, {"string": "long;", "links": [0], "variables": ["long"], "ids": ["lp"], "nodeId": 5, "featuresSelf": ["0"], "operators": [], "constants": ["0"], "features": ["0"]}, {"string": " len = strlen ( s )", "links": [4], "variables": ["s", "strlen"], "ids": ["lp"], "nodeId": 6, "featuresSelf": [], "operators": [], "constants": [], "features": ["%s", "1000000", "in"]}, {"string": " i < len", "links": [6], "variables": ["len", "i"], "ids": ["lp"], "nodeId": 7, "featuresSelf": ["<0"], "operators": ["<"], "constants": ["0"], "features": ["<0"]}, {"string": null, "links": [], "variables": [], "ids": ["lp"], "nodeId": 8, "featuresSelf": ["cn"], "operators": [], "constants": [], "features": ["cn"]}, {"string": " sum + s [ i ] - '0'", "links": [10, 11, 7], "variables": ["i"], "ids": ["lp", "lp"], "nodeId": 9, "featuresSelf": ["++", "-"], "operators": ["++", "-"], "constants": [], "features": ["++", "+", "'0'", "-", "<0"]}, {"string": null, "links": [], "variables": [], "ids": ["lp", "lp"], "nodeId": 10, "featuresSelf": ["'0'"], "operators": [], "constants": ["'0'"], "features": ["'0'"]}, {"string": " sum + s [ i ]", "links": [6, 9, 9], "variables": ["s", "i", "sum"], "ids": ["lp", "lp"], "nodeId": 11, "featuresSelf": ["+"], "operators": ["+"], "constants": [], "features": ["%s", "<0", "in", "++", "+", "-", "1000000"]}, {"string": " sum % 9", "links": [11], "variables": ["r", "sum"], "ids": ["lp"], "nodeId": 12, "featuresSelf": ["%9"], "operators": ["%"], "constants": ["9"], "features": ["+", "%9"]}, {"string": " sum > 9", "links": [12], "variables": ["sum"], "ids": ["lp"], "nodeId": 13, "featuresSelf": ["icn", ">9"], "operators": [">"], "constants": ["9"], "features": [">9", "+", "%9", "icn"]}, {"string": " 9 - r", "links": [12], "variables": ["r"], "ids": ["lp", "if"], "nodeId": 14, "featuresSelf": ["icn", "out", "out", "<5", "<%d\\n", "<%d\\n", "<9", "-5", "-%d\\n", "-%d\\n", "-9"], "operators": ["<", "-"], "constants": ["5", "%d\\n", "%d\\n", "9"], "features": ["<%d\\n", "<5", "icn", "<9", "-5", "%9", "out", "-9", "-%d\\n"]}, {"string": " 9 - r", "links": [7, 13, 14], "variables": ["len", "sum", "r"], "ids": ["lp"], "nodeId": 15, "featuresSelf": ["icn", "out", "out", "!=1", "!=%lld\\n", "!=9", "!=%d\\n", "!=5", "!=9", "-1", "-%lld\\n", "-9", "-%d\\n", "-5", "-9", "<1", "<%lld\\n", "<9", "<%d\\n", "<5", "<9", "-1", "-%lld\\n", "-9", "-%d\\n", "-5", "-9"], "operators": ["!=", "-", "<", "-"], "constants": ["1", "%lld\\n", "9", "%d\\n", "5", "9"], "features": ["<%d\\n", "<%lld\\n", "!=%lld\\n", "<0", "<1", "<9", "<5", "%9", ">9", "-%d\\n", "!=9", "icn", "!=1", "+", "!=5", "!=%d\\n", "-5", "-1", "-%lld\\n", "out", "-9"]}, {"string": " return 0", "links": [], "variables": [], "ids": [], "nodeId": 16, "featuresSelf": ["return", "0"], "operators": [], "constants": ["0"], "features": ["0", "return"]}]}