{"nodes": [{"string": "t;", "links": [], "variables": [], "ids": [], "nodeId": 0, "featuresSelf": [], "operators": [], "constants": [], "features": []}, {"string": "scanf", "links": [], "variables": ["t"], "ids": [], "nodeId": 1, "featuresSelf": ["in", "&%d"], "operators": ["&"], "constants": ["%d"], "features": ["&%d", "in"]}, {"string": " while ( t -- )", "links": [1], "variables": ["t"], "ids": [], "nodeId": 2, "featuresSelf": ["cn", "--"], "operators": ["--"], "constants": [], "features": ["--", "&%d", "cn", "in"]}, {"string": "char m[25001];", "links": [], "variables": ["m", "["], "ids": ["lp"], "nodeId": 3, "featuresSelf": ["25001", "25001"], "operators": [], "constants": ["25001", "25001"], "features": ["25001"]}, {"string": "scanf", "links": [3], "variables": ["m", "w"], "ids": ["lp"], "nodeId": 4, "featuresSelf": ["in", "%s%s"], "operators": [], "constants": ["%s%s"], "features": ["%s%s", "25001", "in"]}, {"string": "lenw;", "links": [], "variables": [], "ids": ["lp"], "nodeId": 5, "featuresSelf": ["0"], "operators": [], "constants": ["0"], "features": ["0"]}, {"string": " lenw = strlen ( w )", "links": [4], "variables": ["w", "strlen"], "ids": ["lp"], "nodeId": 6, "featuresSelf": [], "operators": [], "constants": [], "features": ["%s%s", "in"]}, {"string": " lenm = strlen ( m )", "links": [4, 6], "variables": ["m", "strlen"], "ids": ["lp"], "nodeId": 7, "featuresSelf": [], "operators": [], "constants": [], "features": ["%s%s", "25001", "in"]}, {"string": " i < lenw", "links": [6], "variables": ["lenw", "i"], "ids": ["lp"], "nodeId": 8, "featuresSelf": ["<0"], "operators": ["<"], "constants": ["0"], "features": ["<0"]}, {"string": null, "links": [], "variables": [], "ids": ["lp"], "nodeId": 9, "featuresSelf": ["cn"], "operators": [], "constants": [], "features": ["cn"]}, {"string": null, "links": [8], "variables": ["i"], "ids": ["lp", "lp"], "nodeId": 10, "featuresSelf": ["++"], "operators": ["++"], "constants": [], "features": ["++", "<0"]}, {"string": " m [ 0 ] == w [ i ]", "links": [6, 10, 7], "variables": ["w", "i", "m"], "ids": ["lp", "lp"], "nodeId": 11, "featuresSelf": ["icn", "==0"], "operators": ["=="], "constants": ["0"], "features": ["%s%s", "icn", "<0", "in", "++", "==0", "25001"]}, {"string": " j < lenm", "links": [7], "variables": ["lenm", "j"], "ids": ["lp", "lp", "if"], "nodeId": 12, "featuresSelf": ["<0"], "operators": ["<"], "constants": ["0"], "features": ["<0"]}, {"string": null, "links": [], "variables": [], "ids": ["lp", "lp", "if"], "nodeId": 13, "featuresSelf": ["cn"], "operators": [], "constants": [], "features": ["cn"]}, {"string": null, "links": [12], "variables": ["j"], "ids": ["lp", "lp", "if", "lp"], "nodeId": 14, "featuresSelf": ["++"], "operators": ["++"], "constants": [], "features": ["++", "<0"]}, {"string": " m [ j ] == w [ i ]", "links": [11, 11, 11, 14], "variables": ["w", "i", "m", "j"], "ids": ["lp", "lp", "if", "lp"], "nodeId": 15, "featuresSelf": ["icn", "=="], "operators": ["=="], "constants": [], "features": ["%s%s", "icn", "<0", "==", "==0", "++", "in", "25001"]}, {"string": " ans = 1", "links": [], "variables": [], "ids": ["lp", "lp", "if", "lp", "if"], "nodeId": 16, "featuresSelf": ["1"], "operators": [], "constants": ["1"], "features": ["1"]}, {"string": " i + 1", "links": [15], "variables": ["i"], "ids": ["lp", "lp", "if", "lp", "if"], "nodeId": 17, "featuresSelf": ["+1"], "operators": ["+"], "constants": ["1"], "features": ["++", "+1", "icn", "<0", "==", "==0"]}, {"string": " ans = 1", "links": [], "variables": [], "ids": ["lp", "lp", "if", "lp"], "nodeId": 18, "featuresSelf": ["1"], "operators": [], "constants": ["1"], "features": ["1"]}, {"string": " i + 1", "links": [17], "variables": ["i"], "ids": ["lp", "lp", "if", "lp"], "nodeId": 19, "featuresSelf": ["+1"], "operators": ["+"], "constants": ["1"], "features": ["==", "+1", "icn", "<0", "++", "==0"]}, {"string": " j - 1", "links": [15], "variables": ["j"], "ids": ["lp", "lp", "if", "lp"], "nodeId": 20, "featuresSelf": ["-1"], "operators": ["-"], "constants": ["1"], "features": ["==", "++", "-1", "icn", "<0"]}, {"string": " i > lenw", "links": [8, 19], "variables": ["lenw", "i"], "ids": ["lp", "lp", "if", "lp"], "nodeId": 21, "featuresSelf": ["icn", ">"], "operators": [">"], "constants": [], "features": ["icn", "<0", "++", "==0", "==", "+1", ">"]}, {"string": " ans = 0", "links": [], "variables": [], "ids": ["lp", "lp", "if", "lp", "if"], "nodeId": 22, "featuresSelf": ["0"], "operators": [], "constants": ["0"], "features": ["0"]}, {"string": " break", "links": [], "variables": [], "ids": ["lp", "lp", "if", "lp", "if"], "nodeId": 23, "featuresSelf": ["break"], "operators": [], "constants": [], "features": ["break"]}, {"string": " ans == 1", "links": [22], "variables": ["ans"], "ids": ["lp", "lp"], "nodeId": 24, "featuresSelf": ["icn", "break", "==1"], "operators": ["=="], "constants": ["1"], "features": ["break", "0", "==1", "icn"]}, {"string": " ans == 0", "links": [24], "variables": ["ans"], "ids": ["lp"], "nodeId": 25, "featuresSelf": ["icn", "out", "out", "==0", "==NO\\n", "==YES\\n"], "operators": ["=="], "constants": ["0", "NO\\n", "YES\\n"], "features": ["icn", "==NO\\n", "==1", "==0", "break", "==YES\\n", "out"]}]}