{"nodes": [{"ids": [], "features": [], "links": [], "string": "B;", "variables": [], "operators": [], "nodeId": 0, "constants": [], "featuresSelf": []}, {"ids": [], "features": [], "links": [], "string": "char s[100001];", "variables": ["s"], "operators": [], "nodeId": 1, "constants": ["100001"], "featuresSelf": []}, {"ids": [], "features": [], "links": [], "string": "scanf", "variables": ["B"], "operators": ["&"], "nodeId": 2, "constants": ["%d"], "featuresSelf": ["in"]}, {"ids": [], "features": [], "links": [], "string": " while ( B -- )", "variables": ["B"], "operators": ["--"], "nodeId": 3, "constants": [], "featuresSelf": ["cn", "loop"]}, {"ids": ["lp"], "features": [], "links": [], "string": " sum = 0", "variables": [], "operators": [], "nodeId": 4, "constants": ["0"], "featuresSelf": []}, {"ids": ["lp"], "features": [], "links": [], "string": "scanf", "variables": ["s"], "operators": [], "nodeId": 5, "constants": ["%s"], "featuresSelf": ["in"]}, {"ids": ["lp"], "features": [], "links": [], "string": " len = strlen ( s )", "variables": ["s", "strlen"], "operators": [], "nodeId": 6, "constants": [], "featuresSelf": []}, {"ids": ["lp"], "features": [], "links": [], "string": " i < len", "variables": ["len", "i"], "operators": ["<"], "nodeId": 7, "constants": ["0"], "featuresSelf": []}, {"ids": ["lp"], "features": [], "links": [], "string": null, "variables": [], "operators": [], "nodeId": 8, "constants": [], "featuresSelf": ["cn"]}, {"ids": ["lp", "lp"], "features": [], "links": [10, 11], "string": " sum + s [ i ] - 48", "variables": ["i"], "operators": ["++", "-"], "nodeId": 9, "constants": [], "featuresSelf": []}, {"ids": ["lp", "lp"], "features": [], "links": [], "string": null, "variables": [], "operators": [], "nodeId": 10, "constants": ["48"], "featuresSelf": []}, {"ids": ["lp", "lp"], "features": [], "links": [], "string": " sum + s [ i ]", "variables": ["s", "i", "sum"], "operators": ["+"], "nodeId": 11, "constants": [], "featuresSelf": []}, {"ids": ["lp"], "features": [], "links": [], "string": " sum < 5", "variables": ["sum"], "operators": ["<"], "nodeId": 12, "constants": ["5"], "featuresSelf": ["icn"]}, {"ids": ["lp", "if"], "features": [], "links": [], "string": " 9 - sum", "variables": ["len", "sum"], "operators": ["==", "-"], "nodeId": 13, "constants": ["1", "%d\\n", "%d\\n", "9"], "featuresSelf": ["icn", "out", "out"]}, {"ids": ["lp"], "features": [], "links": [], "string": " sum % 9", "variables": ["sum"], "operators": ["%"], "nodeId": 14, "constants": ["9"], "featuresSelf": []}, {"ids": ["lp"], "features": [], "links": [], "string": " 9 - sum", "variables": ["sum"], "operators": ["<", "-"], "nodeId": 15, "constants": ["5", "%d\\n", "%d\\n", "9"], "featuresSelf": ["icn", "out", "out"]}, {"ids": [], "features": [], "links": [], "string": " return 0", "variables": [], "operators": [], "nodeId": 16, "constants": ["0"], "featuresSelf": ["return"]}], "features": [{"controlContextEC": [":", ":100001", ":1;&;%d", ":1;--;", "lp:0", "lp:%s", "lp:", "lp:2;<;0", "lp:", "lplp:1;++;1;-;", "lplp:48", "lplp:3;+;", "lp:1;<;5", "lpif:2;==;2;-;1%d\\n%d\\n9", "lp:1;%;9", "lp:1;<;1;-;5%d\\n%d\\n9", ":0"], "expr": ["", "100001", "1;&;%d", "1;--;", "0", "%s", "", "2;<;0", "", "1;++;1;-;", "48", "3;+;", "1;<;5", "2;==;2;-;1%d\\n%d\\n9", "1;%;9", "1;<;1;-;5%d\\n%d\\n9", "0"], "controlContextBC": [":100001", ":&", ":%d", ":--", "lp:0", "lp:%s", "lp:<", "lp:0", "lplp:++", "lplp:-", "lplp:48", "lplp:+", "lp:<", "lp:5", "lpif:==", "lpif:-", "lpif:1", "lpif:%d\\n", "lpif:%d\\n", "lpif:9", "lp:%", "lp:9", "lp:<", "lp:-", "lp:5", "lp:%d\\n", "lp:%d\\n", "lp:9", ":0"], "exprDepend": ["3;+;#1;%;9", "1;<;5#1;%;9", "2;==;2;-;1%d\\n%d\\n9#1;%;9"], "basic": ["100001", "&", "%d", "--", "loop", "0", "%s", "<", "0", "loop", "++", "-", "48", "+", "<", "5", "==", "-", "1", "%d\\n", "%d\\n", "9", "%", "9", "<", "-", "5", "%d\\n", "%d\\n", "9", "0"]}]}