{"nodes": [{"string": " * _p -> _p ++ = _c", "links": [], "variables": ["_c", "_p", "__swbuf"], "ids": [], "nodeId": 0, "featuresSelf": ["icn", "return", "return"], "operators": ["||", "&&", "!=", ">=", ">=", "--", "++", "++"], "constants": ["'\\n'", "0"], "features": []}, {"string": "t;", "links": [], "variables": [], "ids": [], "nodeId": 1, "featuresSelf": [], "operators": [], "constants": [], "features": []}, {"string": "scanf", "links": [], "variables": ["t"], "ids": [], "nodeId": 2, "featuresSelf": ["in"], "operators": ["&"], "constants": ["%d"], "features": []}, {"string": " i <= t", "links": [], "variables": ["i", "t"], "ids": [], "nodeId": 3, "featuresSelf": [], "operators": ["<="], "constants": ["1"], "features": []}, {"string": null, "links": [], "variables": [], "ids": [], "nodeId": 4, "featuresSelf": ["cn"], "operators": [], "constants": [], "features": []}, {"string": null, "links": [], "variables": ["i"], "ids": ["lp"], "nodeId": 5, "featuresSelf": [], "operators": ["++"], "constants": [], "features": []}, {"string": "ln;", "links": [], "variables": [], "ids": ["lp"], "nodeId": 6, "featuresSelf": [], "operators": [], "constants": ["0"], "features": []}, {"string": "scanf", "links": [], "variables": ["ln"], "ids": ["lp"], "nodeId": 7, "featuresSelf": ["in"], "operators": ["&"], "constants": ["%d"], "features": []}, {"string": "a;", "links": [], "variables": ["a", "ln"], "ids": ["lp"], "nodeId": 8, "featuresSelf": [], "operators": [], "constants": [], "features": []}, {"string": " j < ln", "links": [], "variables": ["j", "ln"], "ids": ["lp"], "nodeId": 9, "featuresSelf": [], "operators": ["<"], "constants": ["0"], "features": []}, {"string": null, "links": [], "variables": [], "ids": ["lp"], "nodeId": 10, "featuresSelf": ["cn"], "operators": [], "constants": [], "features": []}, {"string": null, "links": [], "variables": ["j"], "ids": ["lp", "lp"], "nodeId": 11, "featuresSelf": [], "operators": ["++"], "constants": [], "features": []}, {"string": "scanf", "links": [], "variables": ["a", "j"], "ids": ["lp", "lp"], "nodeId": 12, "featuresSelf": ["in"], "operators": ["&"], "constants": ["%d"], "features": []}, {"string": "l;", "links": [], "variables": [], "ids": ["lp"], "nodeId": 13, "featuresSelf": [], "operators": [], "constants": [], "features": []}, {"string": "scanf", "links": [], "variables": ["l"], "ids": ["lp"], "nodeId": 14, "featuresSelf": ["in"], "operators": ["&"], "constants": ["%d"], "features": []}, {"string": "b;", "links": [], "variables": ["b", "l"], "ids": ["lp"], "nodeId": 15, "featuresSelf": [], "operators": [], "constants": [], "features": []}, {"string": " k < l", "links": [], "variables": ["k", "l"], "ids": ["lp"], "nodeId": 16, "featuresSelf": [], "operators": ["<"], "constants": ["0"], "features": []}, {"string": null, "links": [], "variables": [], "ids": ["lp"], "nodeId": 17, "featuresSelf": ["cn"], "operators": [], "constants": [], "features": []}, {"string": null, "links": [], "variables": ["k"], "ids": ["lp", "lp"], "nodeId": 18, "featuresSelf": [], "operators": ["++"], "constants": [], "features": []}, {"string": "scanf", "links": [], "variables": ["b", "k"], "ids": ["lp", "lp"], "nodeId": 19, "featuresSelf": ["in"], "operators": ["&"], "constants": ["%d"], "features": []}, {"string": " j < l", "links": [], "variables": ["j", "l"], "ids": ["lp"], "nodeId": 20, "featuresSelf": [], "operators": ["<"], "constants": ["0"], "features": []}, {"string": null, "links": [], "variables": [], "ids": ["lp"], "nodeId": 21, "featuresSelf": ["cn"], "operators": [], "constants": [], "features": []}, {"string": null, "links": [], "variables": ["j"], "ids": ["lp", "lp"], "nodeId": 22, "featuresSelf": [], "operators": ["++"], "constants": [], "features": []}, {"string": " k < ln", "links": [], "variables": ["k", "ln"], "ids": ["lp", "lp"], "nodeId": 23, "featuresSelf": [], "operators": ["<"], "constants": ["0"], "features": []}, {"string": null, "links": [], "variables": [], "ids": ["lp", "lp"], "nodeId": 24, "featuresSelf": ["cn"], "operators": [], "constants": [], "features": []}, {"string": null, "links": [], "variables": ["k"], "ids": ["lp", "lp", "lp"], "nodeId": 25, "featuresSelf": [], "operators": ["++"], "constants": [], "features": []}, {"string": " a [ k ] == b [ j ]", "links": [], "variables": ["b", "j", "a", "k"], "ids": ["lp", "lp", "lp"], "nodeId": 26, "featuresSelf": ["icn"], "operators": ["=="], "constants": [], "features": []}, {"string": " count ++", "links": [], "variables": ["count"], "ids": ["lp", "lp", "lp", "if"], "nodeId": 27, "featuresSelf": [], "operators": ["++"], "constants": [], "features": []}, {"string": " break", "links": [], "variables": [], "ids": ["lp", "lp", "lp", "if"], "nodeId": 28, "featuresSelf": ["break"], "operators": [], "constants": [], "features": []}, {"string": " count == l", "links": [], "variables": ["l", "count"], "ids": ["lp"], "nodeId": 29, "featuresSelf": ["icn"], "operators": ["=="], "constants": [], "features": []}, {"string": "printf", "links": [], "variables": [], "ids": ["lp", "if"], "nodeId": 30, "featuresSelf": ["out"], "operators": [], "constants": ["YES\\n"], "features": []}, {"string": "printf", "links": [], "variables": [], "ids": ["lp"], "nodeId": 31, "featuresSelf": ["out"], "operators": [], "constants": ["NO\\n"], "features": []}, {"string": " return 0", "links": [], "variables": [], "ids": [], "nodeId": 32, "featuresSelf": ["return"], "operators": [], "constants": ["0"], "features": []}], "features": [{"controlContextEC": [":3;||;3;&&;3;!=;3;>=;3;>=;3;--;3;++;3;++;'\\n'0", ":3;||;3;&&;3;!=;3;>=;3;>=;3;--;3;++;3;++;'\\n'0", ":", ":1;&;%d", ":2;<=;1", ":", "lp:1;++;", "lp:0", "lp:1;&;%d", "lp:", "lp:2;<;0", "lp:", "lplp:1;++;", "lplp:2;&;%d", "lp:", "lp:1;&;%d", "lp:", "lp:2;<;0", "lp:", "lplp:1;++;", "lplp:2;&;%d", "lp:2;<;0", "lp:", "lplp:1;++;", "lplp:2;<;0", "lplp:", "lplplp:1;++;", "lplplp:4;==;", "lplplpif:1;++;", "lplplpif:", "lp:2;==;", "lpif:YES\\n", "lp:NO\\n", ":0"], "expr": ["3;||;3;&&;3;!=;3;>=;3;>=;3;--;3;++;3;++;'\\n'0", "3;||;3;&&;3;!=;3;>=;3;>=;3;--;3;++;3;++;'\\n'0", "", "1;&;%d", "2;<=;1", "", "1;++;", "0", "1;&;%d", "", "2;<;0", "", "1;++;", "2;&;%d", "", "1;&;%d", "", "2;<;0", "", "1;++;", "2;&;%d", "2;<;0", "", "1;++;", "2;<;0", "", "1;++;", "4;==;", "1;++;", "", "2;==;", "YES\\n", "NO\\n", "0"], "basic": ["||", "&&", "!=", ">=", ">=", "--", "++", "++", "'\\n'", "0", "||", "&&", "!=", ">=", ">=", "--", "++", "++", "'\\n'", "0", "&", "%d", "<=", "1", "loop", "++", "0", "&", "%d", "<", "0", "loop", "++", "&", "%d", "&", "%d", "<", "0", "loop", "++", "&", "%d", "<", "0", "loop", "++", "<", "0", "loop", "++", "==", "++", "==", "YES\\n", "NO\\n", "0"], "exprDepend": [], "controlContextBC": [":||", ":&&", ":!=", ":>=", ":>=", ":--", ":++", ":++", ":'\\n'", ":0", ":||", ":&&", ":!=", ":>=", ":>=", ":--", ":++", ":++", ":'\\n'", ":0", ":&", ":%d", ":<=", ":1", "lp:++", "lp:0", "lp:&", "lp:%d", "lp:<", "lp:0", "lplp:++", "lplp:&", "lplp:%d", "lp:&", "lp:%d", "lp:<", "lp:0", "lplp:++", "lplp:&", "lplp:%d", "lp:<", "lp:0", "lplp:++", "lplp:<", "lplp:0", "lplplp:++", "lplplp:==", "lplplpif:++", "lp:==", "lpif:YES\\n", "lp:NO\\n", ":0"]}]}